toolkitz/__init__.py
toolkitz/core.py
toolkitz-0.1.5.dist-info/METADATA
toolkitz-0.1.5.dist-info/WHEEL
toolkitz-0.1.5.dist-info/top_level.txt
toolkitz-0.1.5.dist-info/RECORD
