Metadata-Version: 2.4
Name: toolkitz
Version: 0.1.5
Summary: Add your description here
Requires-Python: >=3.12
Requires-Dist: agno>=2.2.13
Requires-Dist: anyio>=4.11.0
Requires-Dist: fastapi>=0.121.1
Requires-Dist: pytest>=9.0.0
Requires-Dist: pytest-asyncio>=1.3.0
Requires-Dist: pytest-tornasync>=0.6.0.post2
Requires-Dist: sqlalchemy>=2.0.44
Requires-Dist: toml>=0.10.2
Requires-Dist: uvicorn>=0.38.0
